paff/__init__.py
paff/cli.py
paff/core.py
paff/data.py
paff/settings.py
paff-0.0.2.dist-info/LICENSE
paff-0.0.2.dist-info/METADATA
paff-0.0.2.dist-info/WHEEL
paff-0.0.2.dist-info/entry_points.txt
paff-0.0.2.dist-info/top_level.txt
paff-0.0.2.dist-info/RECORD
